reclass_rs-0.10.1.dist-info/METADATA
reclass_rs-0.10.1.dist-info/WHEEL
reclass_rs-0.10.1.dist-info/licenses/LICENSE
reclass_rs/__init__.py
reclass_rs/__init__.pyi
reclass_rs/py.typed
reclass_rs/reclass_rs.cpython-313-arm-linux-gnueabihf.so
reclass_rs/reclass_rs.pyi
reclass_rs-0.10.1.dist-info/RECORD
