Metadata-Version: 2.4
Name: reclass-rs
Version: 0.10.1
Classifier: Programming Language :: Rust
Classifier: Programming Language :: Python :: Implementation :: CPython
Classifier: Programming Language :: Python :: Implementation :: PyPy
License-File: LICENSE
Summary: Reclass defines a syntax and directory structure for recursively merging YAML data sources.
Keywords: yaml,reclass,hierarchical config
Author: VSHN AG <info@vshn.ch>
Author-email: VSHN AG <info@vshn.ch>
License: BSD-3-Clause
Requires-Python: >=3.9
Project-URL: Source Code, https://github.com/projectsyn/reclass-rs
